{"rfc_id":"AAOS-RFC-0001","registry_id":"C5","role_count":3,"roles":[{"id":"AAOS-L2ROLE-A","name":"Admission and Arbitration","responsibilities":["validate exact subject and candidate identity","validate Principal, Authority, Grant, Policy, state, time, scope, resource, budget, risk, target, tool, credential, environment, side-effect, and trajectory context","produce bounded admission outcomes"],"permitted_outcomes":["allow","deny","restrict","quarantine","require_step_up","human_review_required"],"outcome_semantics":{"allow":"admission outcome value; not independent authorization and not a canonical verb","human_review_required":"routing/review outcome value; not Authority grant and not a canonical verb","admit":"canonical governance operation"},"prohibited":["create L0 intent","invent L1 Authority","silently mutate candidate","dispatch operation","execute effect"],"handoff_to":"AAOS-L2ROLE-O","handoff_requirements":["exact subject binding","candidate binding","Authority/Grant/Policy binding","state and time binding","trajectory binding"],"mapped_requirements":["AAOS-REQ-0001-013","AAOS-REQ-0001-014","AAOS-REQ-0001-015","AAOS-REQ-0001-016"]},{"id":"AAOS-L2ROLE-O","name":"Orchestration and Coordination","responsibilities":["bounded workflow coordination","scheduling","dependency ordering","timeout coordination","retry coordination","fallback coordination","compensation coordination","pause, resume, abandonment, and cancellation coordination"],"permitted":["transport an existing exact admission or Grant without altering Authority, candidate, state, scope, validity, or trajectory bindings"],"prohibited":["approve","renew Authority","widen Authority","reinterpret Authority","self-issue Authority"],"required_invariants":["workflow_continues!=Authority_remains_fresh","retry_available!=retry_authorized","resume_possible!=resume_admitted","fallback_configured!=fallback_permitted"],"handoff_from":"AAOS-L2ROLE-A","handoff_to":"AAOS-L2ROLE-E","handoff_requirements":["current admission","unaltered exact bindings","bounded command intent","current authority semantics"],"mapped_requirements":["AAOS-REQ-0001-017","AAOS-REQ-0001-018","AAOS-REQ-0001-019","AAOS-REQ-0001-020"]},{"id":"AAOS-L2ROLE-E","name":"Enforcement and Dispatch","responsibilities":["validate exact bounded command against current admission","tool-lane and execution-lane restriction","dispatch","quota enforcement","interruption","cancellation","kill","freeze","isolation","containment","egress closure","Action Provenance","residual-effect reporting"],"prohibited":["self-approve","invent missing Authority","silently widen command","treat capability availability as permission","self-verify containment or finality"],"handoff_from":"AAOS-L2ROLE-O","handoff_to":"L3/L4 bounded computation or external effect","handoff_requirements":["exact command","current admission","current Authority and Policy bindings","enforcement constraints","provenance obligations"],"mapped_requirements":["AAOS-REQ-0001-021","AAOS-REQ-0001-022","AAOS-REQ-0001-023","AAOS-REQ-0001-024"]}],"logical_separation_required":true,"physical_colocation_permitted":true,"physical_colocation_constraints":["roles remain independently distinguishable","Authority boundaries remain explicit","handoffs remain traceable","evidence obligations remain separable","conformance claims remain role-specific"],"required_distinctions":["L2-A_admission!=L2-O_orchestration","L2-O_orchestration!=L2-E_dispatch","L2-E_dispatch!=L3/L4_execution","capability_available!=permission","retry_available!=retry_authorized"]}